xaif_test/__init__.py
xaif_test/xaif.py
xaif_test-0.0.1.dist-info/METADATA
xaif_test-0.0.1.dist-info/WHEEL
xaif_test-0.0.1.dist-info/RECORD
