Metadata-Version: 2.1
Name: xaif_test
Version: 0.0.1
Summary: xaif package
Project-URL: Homepage, https://github.com/debelatesfaye/xaif
Project-URL: Issues, https://github.com/debelatesfaye/xaif/issues
Author-email: DEBELA <dabookoo@gmail.com>
Classifier: License :: OSI Approved :: MIT License
Classifier: Operating System :: OS Independent
Classifier: Programming Language :: Python :: 3
Requires-Python: >=3.8
